desmos_studio/__init__.py
desmos_studio/cli.py
desmos_studio-1.2.3.dist-info/licenses/LICENSE
tests/__init__.py
tests/test_cli.py
desmos_studio-1.2.3.dist-info/METADATA
desmos_studio-1.2.3.dist-info/WHEEL
desmos_studio-1.2.3.dist-info/entry_points.txt
desmos_studio-1.2.3.dist-info/top_level.txt
desmos_studio-1.2.3.dist-info/RECORD
