Metadata-Version: 2.4
Name: desmos-studio
Version: 1.2.3
Summary: Convert images and videos to mathematical curves for Desmos or matplotlib
Home-page: https://github.com/yusuff-bot/desmos-studio
Author: Yusuf Sabuwala
Author-email: yusuff.0279@gmail.com
License: MIT
Project-URL: Bug Reports, https://github.com/yourusername/image2curves/issues
Project-URL: Source, https://github.com/yourusername/image2curves
Project-URL: Documentation, https://github.com/yourusername/image2curves#readme
Keywords: image tracing,desmos,matplotlib,svg,potrace,bezier curves
Classifier: Development Status :: 4 - Beta
Classifier: Intended Audience :: Education
Classifier: Intended Audience :: Science/Research
Classifier: License :: OSI Approved :: MIT License
Classifier: Programming Language :: Python :: 3
Classifier: Programming Language :: Python :: 3.7
Classifier: Programming Language :: Python :: 3.8
Classifier: Programming Language :: Python :: 3.9
Classifier: Programming Language :: Python :: 3.10
Classifier: Programming Language :: Python :: 3.11
Classifier: Topic :: Scientific/Engineering :: Visualization
Classifier: Topic :: Multimedia :: Graphics :: Graphics Conversion
Requires-Python: >=3.7
License-File: LICENSE
Requires-Dist: matplotlib>=3.0.0
Requires-Dist: svgpathtools>=1.4.0
Requires-Dist: opencv-python>=4.5.0
Requires-Dist: numpy>=1.19.0
Provides-Extra: dev
Requires-Dist: pytest>=6.0; extra == "dev"
Requires-Dist: black; extra == "dev"
Requires-Dist: flake8; extra == "dev"
Requires-Dist: twine; extra == "dev"
Requires-Dist: build; extra == "dev"
Provides-Extra: video
Requires-Dist: yt-dlp>=2023.1.0; extra == "video"
Dynamic: author
Dynamic: author-email
Dynamic: classifier
Dynamic: description
Dynamic: description-content-type
Dynamic: home-page
Dynamic: keywords
Dynamic: license
Dynamic: license-file
Dynamic: project-url
Dynamic: provides-extra
Dynamic: requires-dist
Dynamic: requires-python
Dynamic: summary
